{
  "updatedAt": "2026-07-18T03:25:41.636Z",
  "assets": {
    "BTC": {
      "exchangeNetFlow1dUsd": -83083448,
      "exchangeNetFlow7dUsd": 230919573,
      "exchangeNetFlowZ": -0.9,
      "exchangeLean": "neutral",
      "whaleNetFlow7dUsd": 0,
      "whaleAccumulationScore": 44.8,
      "whaleLean": "neutral",
      "exchangeReserveAmount": 572067.41,
      "reserveChange30dPct": null,
      "reserveLean": "neutral",
      "priceChange7dPct": -0.29,
      "divergence": "none",
      "samples": 23
    },
    "ETH": {
      "exchangeNetFlow1dUsd": -75795487,
      "exchangeNetFlow7dUsd": -93600485,
      "exchangeNetFlowZ": -2.1,
      "exchangeLean": "bullish",
      "whaleNetFlow7dUsd": -62,
      "whaleAccumulationScore": 39.4,
      "whaleLean": "bearish",
      "exchangeReserveAmount": 4213328.59,
      "reserveChange30dPct": null,
      "reserveLean": "neutral",
      "priceChange7dPct": 2.65,
      "divergence": "bearish",
      "samples": 23
    },
    "USDT": {
      "exchangeNetFlow1dUsd": 301753199,
      "exchangeNetFlow7dUsd": 579188840,
      "exchangeNetFlowZ": 1.13,
      "exchangeLean": "bearish",
      "whaleNetFlow7dUsd": -845612611,
      "whaleAccumulationScore": 51.7,
      "whaleLean": "neutral",
      "exchangeReserveAmount": 21563348446.11,
      "reserveChange30dPct": null,
      "reserveLean": "neutral",
      "priceChange7dPct": -0.01,
      "divergence": "none",
      "samples": 23
    },
    "USDC": {
      "exchangeNetFlow1dUsd": 0,
      "exchangeNetFlow7dUsd": 0,
      "exchangeNetFlowZ": 0,
      "exchangeLean": "neutral",
      "whaleNetFlow7dUsd": -38477723,
      "whaleAccumulationScore": 78.3,
      "whaleLean": "bullish",
      "exchangeReserveAmount": 0,
      "reserveChange30dPct": null,
      "reserveLean": "neutral",
      "priceChange7dPct": 0,
      "divergence": "none",
      "samples": 23
    },
    "SOL": {
      "exchangeNetFlow1dUsd": 2624387,
      "exchangeNetFlow7dUsd": 50134288,
      "exchangeNetFlowZ": 0.2,
      "exchangeLean": "neutral",
      "whaleNetFlow7dUsd": 718766,
      "whaleAccumulationScore": 46.3,
      "whaleLean": "neutral",
      "exchangeReserveAmount": 11362597.09,
      "reserveChange30dPct": null,
      "reserveLean": "neutral",
      "priceChange7dPct": -3.15,
      "divergence": "bullish",
      "samples": 23
    }
  },
  "dryPowder": {
    "usd": 88263016703,
    "change7dPct": 0.18
  }
}
